{
    "Требования": "",
    "Цели квеста": "Убить 20 бойцов ЧВК, используя пистолет-пулемет СР-2М \"Вереск\" с глушителем и коллиматорным прицелом КП-СР2",
    "Как выполнить квест": "ОТКРЫВАЕТСЯ ЧЕРЕЗ НЕКОТОРОЕ ВРЕМЯ Нужно убивать ЧВК с помощью сборки СР-2М \"Вереск\" с  коллиматорным прицелом КП-СР 2 и глушителем СВ-1381 на Улицах Таркова Тест-Драйв часть 2 Тест-Драйв часть 2",
    "Ссылки на изображения": [
        "https://minio.tarkov.help/production/img/articles/SR2M_FSB_Icon.webp"
    ],
    "Награды за квест": "\n+28000 Опыта\n\n+0.02 Репутации у Прапора\n\n300000 Рублей\n"
}